pytaobao/__init__.py
pytaobao/auth.py
pytaobao/exceptions.py
pytaobao/helper.py
pytaobao/transport.py
pytaobao/apis/__init__.py
pytaobao/apis/base.py
pytaobao/apis/rate.py
pytaobao/apis/tmc.py
pytaobao/apis/trade.py
pytaobao-1.0.4.dist-info/LICENSE
pytaobao-1.0.4.dist-info/METADATA
pytaobao-1.0.4.dist-info/WHEEL
pytaobao-1.0.4.dist-info/top_level.txt
pytaobao-1.0.4.dist-info/RECORD
