Metadata-Version: 2.1
Name: pytaobao
Version: 1.0.4
Summary: voom backend
Home-page: https://github.com/fatelei/pytaobao
Author: fatelei
Author-email: fatelei@gmail.com
License: PRIVATE
Platform: UNKNOWN
